Workbook
Name _Hlk32486461: Proposal!#REF!
Name GRAND: #REF!
Name OLE_LINK1: Proposal!#REF!
Name Print_Area_MI: #REF!
Name Print_Titles_MI: #REF!,#REF!
Name xx: '[1]AIA G702'!$73:$380,'[1]AIA G702'!$C$5:$DH$16389

Sheet RECAP
J1: Quote #: | K1: E26-XXX
J2: Date: | K2: =TODAY() -> 46238
J3: Estimator:
I4: =_xlfn.XLOOKUP(K3,A56:A57,B56:B57, "E-Mail") -> E-Mail
J5: Profit: | K5: =F53/G53 -> #DIV/0!
I6: Material $/lb: | K6: =(D28+D42)/(Structural!D15+Misc.!D14) -> #DIV/0!
A9: Customer Name: | G9: Project Location: | I9: (Physical Address)
A10: Project Name: | I10: (City, State)
A11: Tons: | B11: =(Structural!D15+Misc.!D14)/2000 -> 0 | C11: Man Hrs: | D11: =Labor!B13+Labor!B27 -> 0 | E11: Man Hrs/Ton: | G11: =D11/B11 -> #DIV/0! | H11: FOB or Erected:
A13: Shop Information:
A14: Structural Labor (hrs.): | D14: =Labor!B13 -> 0 | F14: Structural Labor Rate ($/hr.): | I14: 85
A15: Outsourced Labor (hrs.): | D15: =Outsourced!D14 -> 0 | F15: Outsourced Labor Rate ($/hr.): | I15: 65
A16: Misc Labor (hrs.): | D16: =Labor!B27 -> 0 | F16: Misc. Labor Rate ($/hr.): | I16: 100
A17: Paint Surface (sq. ft.): | F17: 300 | G17: Paint($/gal.): | I17: 38
A18: Galvanizing (lbs.): | D18: =Structural!C15+Misc.!C14 -> 0 | F18: Galvanizing ($/lb.): | I18: 0.45
A19: Galv Freight (del.): | F19: Galv Freight ($/del.): | I19: 1500
A20: Jobsite Freight (del.): | F20: Jobsite Freight ($/del.): | I20: 1000
A22: Pricing Analysis:
A23: Description: | D23: Cost: | E23: Profit Markup | G23: Sell Price: | H23: Cost Per Ton: | I23: % of Job: | J23: Lowest Vendor Quote:
E24: %: | F24: $:
A25: Detailing | E25: 0.1 | F25: =D25*E25 -> 0 | G25: =D25+F25 -> 0 | H25: =IFERROR((D25/$B$11),"") | I25: =IFERROR((G25/$G$53),"")
A26: Engineering | E26: 0.1 | F26: =D26*E26 -> 0 | G26: =D26+F26 -> 0 | H26: =IFERROR((D26/$B$11),"") | I26: =IFERROR((G26/$G$53),"")
A27: BIM | E27: 0.1 | F27: =D27*E27 -> 0 | G27: =D27+F27 -> 0 | H27: =IFERROR((D27/$B$11),"") | I27: =IFERROR((G27/$G$53),"")
A28: Structural Material | D28: =Structural!F15 -> 0 | E28: 0.1 | F28: =D28*E28 -> 0 | G28: =D28+F28 -> 0 | H28: =IFERROR((D28/$B$11),"") | I28: =IFERROR((G28/$G$53),"")
A29: Bolts/Fasteners | D29: =Structural!D25 -> 0 | E29: 0.1 | F29: =D29*E29 -> 0 | G29: =D29+F29 -> 0 | H29: =IFERROR((D29/$B$11),"") | I29: =IFERROR((G29/$G$53),"")
A30: Outsourced Fabrication | E30: 0.1 | F30: =D30*E30 -> 0 | G30: =D30+F30 -> 0 | H30: =IFERROR((D30/$B$11),"") | I30: =IFERROR((G30/$G$53),"")
A31: Structural Fabrication | D31: =Labor!D13-Labor!D5-Labor!D19 -> 0 | E31: 0.1 | F31: =D31*E31 -> 0 | G31: =D31+F31 -> 0 | H31: =IFERROR((D31/$B$11),"") | I31: =IFERROR((G31/$G$53),"")
A32: Galvanizing | D32: =(D18*I18)+(D19*I19) -> 0 | E32: 0.1 | F32: =D32*E32 -> 0 | G32: =D32+F32 -> 0 | H32: =IFERROR((D32/$B$11),"") | I32: =IFERROR((G32/$G$53),"")
A33: Steel Rolling | E33: 0.1 | F33: =D33*E33 -> 0 | G33: =D33+F33 -> 0 | H33: =IFERROR((D33/$B$11),"") | I33: =IFERROR((G33/$G$53),"")
A34: Joist & Deck | D34: ='J&D'!D8 -> 0 | E34: 0.1 | F34: =D34*E34 -> 0 | G34: =D34+F34 -> 0 | H34: =IFERROR((D34/$B$11),"") | I34: =IFERROR((G34/$G$53),"")
A35: Anchor Bolts | D35: =Structural!D35 -> 0 | E35: 0.1 | F35: =D35*E35 -> 0 | G35: =D35+F35 -> 0 | H35: =IFERROR((D35/$B$11),"") | I35: =IFERROR((G35/$G$53),"")
A36: Shop Priming | D36: =((D17/F17)*I17)+Labor!D5+Labor!D19 -> 0 | E36: 0.1 | F36: =D36*E36 -> 0 | G36: =D36+F36 -> 0 | H36: =IFERROR((D36/$B$11),"") | I36: =IFERROR((G36/$G$53),"")
A37: Grating | D37: =Misc.!F6 -> 0 | E37: 0.1 | F37: =D37*E37 -> 0 | G37: =D37+F37 -> 0 | H37: =IFERROR((D37/$B$11),"") | I37: =IFERROR((G37/$G$53),"")
A38: Outsourced Paint | E38: 0.1 | F38: =D38*E38 -> 0 | G38: =D38+F38 -> 0 | H38: =IFERROR((D38/$B$11),"") | I38: =IFERROR((G38/$G$53),"")
A39: Outsourced Shot Blasting | E39: 0.1 | F39: =D39*E39 -> 0 | G39: =D39+F39 -> 0 | H39: =IFERROR((D39/$B$11),"") | I39: =IFERROR((G39/$G$53),"")
A40: Jobsite Freight (Material Delivery) | D40: =D20*I20 -> 0 | E40: 0.1 | F40: =D40*E40 -> 0 | G40: =D40+F40 -> 0 | H40: =IFERROR((D40/$B$11),"") | I40: =IFERROR((G40/$G$53),"")
A41: Misc. Fabrication | D41: =Labor!D27 -> 0 | E41: 0.1 | F41: =D41*E41 -> 0 | G41: =D41+F41 -> 0 | H41: =IFERROR((D41/$B$11),"") | I41: =IFERROR((G41/$G$53),"")
A42: Misc. Material | D42: =Misc.!F14-Misc.!F6 -> 0 | E42: 0.1 | F42: =D42*E42 -> 0 | G42: =D42+F42 -> 0 | H42: =IFERROR((D42/$B$11),"") | I42: =IFERROR((G42/$G$53),"")
A43: Steel Erection | E43: 0.1 | F43: =D43*E43 -> 0 | G43: =D43+F43 -> 0 | H43: =IFERROR((D43/$B$11),"") | I43: =IFERROR((G43/$G$53),"")
A44: Outsourced Misc. Material & Erection | D44: =Outsourced!B14+Outsourced!E14 -> 0 | E44: 0.1 | F44: =D44*E44 -> 0 | G44: =D44+F44 -> 0 | H44: =IFERROR((D44/$B$11),"") | I44: =IFERROR((G44/$G$53),"")
A45: Subcontractor Other | E45: 0.1 | F45: =D45*E45 -> 0 | G45: =D45+F45 -> 0 | H45: =IFERROR((D45/$B$11),"") | I45: =IFERROR((G45/$G$53),"")
A46: Allowance(s) | D46: =Allowance!B10 -> 0 | E46: 0 | F46: =D46 -> 0 | G46: =D46+F46 -> 0 | H46: =IFERROR((D46/$B$11),"") | I46: =IFERROR((G46/$G$53),"")
A47: HSS Contingency | E47: 0.1 | F47: =D47*E47 -> 0 | G47: =D47+F47 -> 0 | H47: =IFERROR((D47/$B$11),"") | I47: =IFERROR((G47/$G$53),"")
A48: Additional Cost: Insurance | D48: ='Addtn''l (AKP)'!D8 -> 0 | E48: 0.1 | F48: =D48*E48 -> 0 | G48: =D48+F48 -> 0 | H48: =IFERROR((D48/$B$11),"") | I48: =IFERROR((G48/$G$53),"")
A49: Additional Cost: LEED; Gov’t Job | D49: ='Addtn''l (AKP)'!E31 -> 0 | E49: 0.1 | F49: =D49*E49 -> 0 | G49: =D49+F49 -> 0 | H49: =IFERROR((D49/$B$11),"") | I49: =IFERROR((G49/$G$53),"")
A50: Subtotal: | D50: =SUM(D25:D49) -> 0 | F50: =SUM(F25:F49) -> 0 | G50: =SUM(G25:G49) -> 0 | H50: =IFERROR((D50/$B$11),"")
A51: Performance/Payment Bond | D51: ='Addtn''l (AKP)'!E17 -> 0 | E51: 0.1 | F51: =D51*E51 -> 0 | G51: =D51+F51 -> 0 | H51: =IFERROR((D51/$B$11),"") | I51: =IFERROR((G51/$G$53),"")
A52: Procore Pay/Textura Fee (including sales tax) | D52: ='Addtn''l (AKP)'!E22 -> 0 | E52: 0.1 | F52: =D52*E52 -> 0 | G52: =D52+F52 -> 0 | H52: =IFERROR((D52/$B$11),"") | I52: =IFERROR((G52/$G$53),"")
A53: Total: | D53: =SUM(D50:D52) -> 0 | F53: =SUM(F50:F52) -> 0 | G53: =SUM(G50:G52) -> 0 | H53: =IFERROR((D53/$B$11),"")
A56: Bill Holfreter | B56: bholtfreter@hancocksteel.com
A57: Paul Hostetter | B57: phostetter@hancocksteel.com

Sheet Structural
A1: Structural Material:
A2: Description: | B2: Weight | E2: $/LB: | F2: Cost ($):
B3: Painted: | C3: Galv. | D3: Total:
A4: Structural Material Package | D4: =SUM(B4:C4) -> 0 | F4: =D4*E4 -> 0
A5: Plate Summary | D5: =SUM(B5:C5) -> 0 | F5: =D5*E5 -> 0
A6: Lintels | D6: =SUM(B6:C6) -> 0 | F6: =D6*E6 -> 0
D7: =SUM(B7:C7) -> 0 | F7: =D7*E7 -> 0
D8: =SUM(B8:C8) -> 0 | F8: =D8*E8 -> 0
D9: =SUM(B9:C9) -> 0 | F9: =D9*E9 -> 0
D10: =SUM(B10:C10) -> 0 | F10: =D10*E10 -> 0
D11: =SUM(B11:C11) -> 0 | F11: =D11*E11 -> 0
D12: =SUM(B12:C12) -> 0 | F12: =D12*E12 -> 0
D13: =SUM(B13:C13) -> 0 | F13: =D13*E13 -> 0
A14: % Escalation Allowance | B14: N/A | C14: N/A | D14: 0 | F14: {=SUM(F4:F13*D14)} -> 0
A15: Totals: | B15: =SUM(B4:B14) -> 0 | C15: =SUM(C4:C14) -> 0 | D15: =SUM(D4:D13) -> 0 | F15: =SUM(F4:F14) -> 0
A17: Bolts/Fasteners:
A18: Description: | B18: Quantity: | C18: $/Unit: | D18: Cost ($):
D19: =B19*C19 -> 0
D20: =B20*C20 -> 0
D21: =B21*C21 -> 0
D22: =B22*C22 -> 0
D23: =B23*C23 -> 0
D24: =B24*C24 -> 0
A25: Total: | D25: =SUM(D19:D24) -> 0
A27: Anchor Bolts:
A28: Description: | B28: Quantity: | C28: $/Unit: | D28: Cost ($):
D29: =B29*C29 -> 0
D30: =B30*C30 -> 0
D31: =B31*C31 -> 0
D32: =B32*C32 -> 0
D33: =B33*C33 -> 0
D34: =B34*C34 -> 0
A35: Total: | D35: =SUM(D29:D34) -> 0

Sheet J&D
A1: Joist:
A2: Description: | B2: Pieces: | C2: Tonnage: | D2: Cost ($):
A8: Totals: | B8: =SUM(B3:B7) -> 0 | C8: =SUM(C3:C7) -> 0 | D8: 0
D9: Enter total amount above from J&D's proposal.
A10: Deck:
A11: Description: | B11: Squares:
A17: Totals: | B17: =SUM(B12:B16) -> 0

Sheet Misc.
A1: Misc. Materials:
A2: Description: | B2: Weight | E2: $/LB: | F2: Cost ($):
B3: Painted: | C3: Galv. | D3: Total:
A4: Steel | D4: =SUM(B4:C4) -> 0 | F4: =D4*E4 -> 0
A5: Plate | D5: =SUM(B5:C5) -> 0 | F5: =D5*E5 -> 0
A6: Grating | D6: =SUM(B6:C6) -> 0 | F6: =D6*E6 -> 0
A7: Bollards | D7: =SUM(B7:C7) -> 0 | F7: =D7*E7 -> 0
D8: =SUM(B8:C8) -> 0 | F8: =D8*E8 -> 0
D9: =SUM(B9:C9) -> 0 | F9: =D9*E9 -> 0
D10: =SUM(B10:C10) -> 0 | F10: =D10*E10 -> 0
D11: =SUM(B11:C11) -> 0 | F11: =D11*E11 -> 0
D12: =SUM(B12:C12) -> 0 | F12: =D12*E12 -> 0
D13: =SUM(B13:C13) -> 0 | F13: =D13*E13 -> 0
A14: Totals: | B14: =SUM(B4:B13) -> 0 | C14: =SUM(C4:C13) -> 0 | D14: =SUM(D4:D13) -> 0 | F14: =SUM(F4:F13) -> 0

Sheet Outsourced
A1: Outsourced Materials, Fabrication & Erection:
A2: Scope Description: | B2: Material ($): | C2: Fabrication: | E2: Erection ($): | F2: Comment:
C3: ($): | D3: Hours:
A14: Totals: | B14: =SUM(B4:B13) -> 0 | C14: =SUM(C4:C13) -> 0 | D14: =SUM(D4:D13) -> 0 | E14: =SUM(E4:E13) -> 0

Sheet Labor
A1: Structural Fabrication:
A2: Description: | B2: Hours: | C2: $/Hour: | D2: Cost ($):
A3: Structural Fabrication | C3: =RECAP!$I$14 -> 85 | D3: =B3*C3 -> 0
A4: Processing Steel | C4: =RECAP!$I$14 -> 85 | D4: =B4*C4 -> 0
A5: Shop Priming | C5: =RECAP!$I$14 -> 85 | D5: =B5*C5 -> 0
A6: Load/Unload Material | C6: =RECAP!$I$14 -> 85 | D6: =B6*C6 -> 0
C7: =RECAP!$I$14 -> 85 | D7: =B7*C7 -> 0
C8: =RECAP!$I$14 -> 85 | D8: =B8*C8 -> 0
C9: =RECAP!$I$14 -> 85 | D9: =B9*C9 -> 0
C10: =RECAP!$I$14 -> 85 | D10: =B10*C10 -> 0
C11: =RECAP!$I$14 -> 85 | D11: =B11*C11 -> 0
C12: =RECAP!$I$14 -> 85 | D12: =B12*C12 -> 0
A13: Totals: | B13: =SUM(B3:B12) -> 0 | D13: =SUM(D3:D12) -> 0
A15: Misc. Fabrication:
A16: Description: | B16: Hours: | C16: $/Hour: | D16: Cost ($):
A17: Misc. Fabrication | C17: =RECAP!$I$16 -> 100 | D17: =B17*C17 -> 0
A18: Processing Steel | C18: =RECAP!$I$14 -> 85 | D18: =B18*C18 -> 0
A19: Shop Priming | C19: =RECAP!$I$14 -> 85 | D19: =B19*C19 -> 0
A20: Load/Unload Material | C20: =RECAP!$I$14 -> 85 | D20: =B20*C20 -> 0
C21: =RECAP!$I$16 -> 100 | D21: =B21*C21 -> 0
C22: =RECAP!$I$16 -> 100 | D22: =B22*C22 -> 0
C23: =RECAP!$I$16 -> 100 | D23: =B23*C23 -> 0
C24: =RECAP!$I$16 -> 100 | D24: =B24*C24 -> 0
C25: =RECAP!$I$16 -> 100 | D25: =B25*C25 -> 0
C26: =RECAP!$I$16 -> 100 | D26: =B26*C26 -> 0
A27: Totals: | B27: =SUM(B17:B26) -> 0 | D27: =SUM(D17:D26) -> 0

Sheet Allowance
A1: ALLOWANCE:
A3: Description: | B3: Cost ($): | C3: Comment:
A10: Totals: | B10: =SUM(B4:B9) -> 0

Sheet Addtn'l (AKP)
A1: Additional Costs:
A2: Insurance: | B2: (Y or N): | C2: Rate: | D2: Cost: | E2: Comment:
A3: Builder's Risk Buy Down: | C3: 3000 | D3: =IF(B3="Y",C3,0) -> 0 | E3: Per year; up to $2M; job scope structural steel, deck, joist, beams, handrails, ladders; Up to $50K; policy deductible $2,500; Over $2M obtain cost from USI Insurance
A4: General Liability: | D4: =IF(B4="Y",C4,0) -> 0 | E4: Additional coverage required
A5: Umbrella: | D5: =IF(B5="Y",C5,0) -> 0 | E5: Additional coverage required
A6: Professional Liability: | D6: =IF(B6="Y",C6,0) -> 0 | E6: Additional coverage required
D7: =IF(B7="Y",C7,0) -> 0
A8: Total: | D8: =SUM(D3:D7) -> 0
A10: Performance / Payment Bond: | B10: (Y or N): | C10: Rate*: | D10: Recap Subtotal: | E10: Cost: | F10: Comment:
D11: =IF(B11="Y",(RECAP!G50+RECAP!G52+'Addtn''l (AKP)'!E36),0) -> 0 | F11: Includes Recap Subtotal, Textura/Procore Pay with OH&P and Sales Tax
A12: $0.01 - $500,000: | C12: 0.0081 | D12: =MIN($D$11,500000) -> 0 | E12: =IFERROR((D12*C12),"") -> 0
A13: $500,001 - $2,500,000: | C13: 0.00567 | D13: =MAX(MIN($D$11-D12,2000000),0) -> 0 | E13: =IFERROR((D13*C13),"") -> 0
A14: $2,500,001 - $5,000,000: | C14: 0.00486 | D14: =MAX(MIN($D$11-SUM($D$12:D13),2500000),0) -> 0 | E14: =IFERROR((D14*C14),"") -> 0
A15: $5,000,00+: | C15: 0.00432 | D15: =MAX($D$11-SUM($D$12:D14),0) -> 0 | E15: =IFERROR((D15*C15),"") -> 0
A16: $7,500,000+ | E16: =IFERROR((D16*#REF!),"")
A17: Total: | E17: =SUM(E12:E16) -> 0
A19: Procore Pay/Textura: | B19: (Y or N): | C19: Fee: | D19: Sales Tax: | E19: Total: | F19: Comment:
A20: Project Pay: | C20: =IF($B$20="Y",((SUM(RECAP!$G$50+RECAP!$G$51)*0.2%)),0) -> 0 | D20: =C20*6.75% -> 0 | E20: =IF(B20="Y",MIN(C20+D20,"$4,270.00"),0) -> 0
A21: Textura: | C21: =IF($B$21="Y",((SUM(RECAP!$G$50+RECAP!$G$51)*0.2%)),0) -> 0 | D21: =C21*6.75% -> 0 | E21: =IF(B21="Y",MIN(C21+D21,"$5,337.50"),0) -> 0
A22: Total: | E22: =E20+E21 -> 0
A24: LEED Level / Government Job: | B24: N/A | C24: Hours: | D24: Rate: | E24: Cost: | F24: Comment:
A25: Certified: | C25: 30 | D25: 50 | E25: =IF($B$24="Certified", C25*D25, 0) -> 0
A26: Silver: | C26: 50 | D26: 50 | E26: =IF($B$24="Silver", C26*D26, 0) -> 0
A27: Gold: | C27: 80 | D27: 50 | E27: =IF($B$24="Gold", C27*D27, 0) -> 0
A28: Platinum: | C28: 120 | D28: 50 | E28: =IF($B$24="Platinum", C28*D28, 0) -> 0
A29: Government Job: | C29: 140 | D29: 50 | E29: =IF($B$24="Government", C29*D29, 0) -> 0
A30: $7,500,000+
A31: Total: | E31: =SUM(E25:E30) -> 0
A33: Sales Tax: | D33: Recap Total: | E33: Total Cost: | F33: Comment:
A34: Tax County/Rate: | B34: Tax Exempt | C34: =VLOOKUP($B$34, $C$39:$D$45, 2, FALSE) -> 0 | D34: =RECAP!G50-RECAP!G43-Outsourced!E14-(Outsourced!E14*RECAP!E44) -> 0 | E34: =IFERROR((D34*C34),"") -> 0 | F34: Sales tax calculated on all except Erection, J&D cost, Procore Pay/Textura fees & Bond cost (if applicable)
A35: Project County/Rate: | D35: =RECAP!D34 -> 0 | E35: =IFERROR((D35*C35),"") -> 0 | F35: Joist & Deck cost (mark-up included above)
A36: Total: | E36: =SUM(E34:E35) -> 0
A38: *Rates effective 03/26/26 | B38: Tax Area: | D38: Tax Rate: | E38: Change Date: | F38: Sales tax rates are subject to change. Ask Anne or Alexia to verify the current rate before quoting to a customer.
C39: Tax Exempt | D39: 0
C40: Hancock | D40: 0.0675
C41: Indiana | D41: 0.07 | E41: 2008
C42: Kentucky | D42: 0.06
C43: Michigan | D43: 0.06 | E43: 1994
C44: UT: American Fork | D44: 0.0745 | E44: Jan. '26
C45: UT: Heber City | D45: 0.0835 | E45: Jan. '26

Sheet Proposal
O2: 813 E Bigelow Avenue
O3: Findlay, OH 45840
O4: Phone: 419-424-1217
A7: Date: | B7: =RECAP!K2 -> 46238 | I7: Proposal Expires: | L7: =B7+6 -> 46244 | N7: Quote #: | Q7: =RECAP!K1 -> E26-XXX
A9: Project: | C9: =RECAP!C10 -> 0 | N9: Customer (Buyer): | R9: =RECAP!C9 -> 0
C10: =RECAP!I10 -> (City, State) | N10: Attention:
A12: Specification Sections:
A13: Drawings Used:
A14: Supplied Cut Sheet:
A19: Addendums:
A21: Includes:
A22: - XX Columns
A23: -
A24: -
A25: -
A26: -
A27: -
A28: -
... A59: + Must Ship Complete by Date:
A61: Alternates: | M61: Allowances:
A63: F.O.B. Jobsite (Supply Only - Not Erected) | V63: F.O.B. Jobsite (Supply Only - Not Erected)
A64: Total Price (Excluding Sales Tax): | R64: =RECAP!G53 -> 0 | V64: Fabricated, Delivered, and Installed
A65: Sales Tax: | R65: ='Addtn''l (AKP)'!E36 -> 0
A66: Total Price (Including Sales Tax): | R66: =SUM(R64:R65) -> 0
A67: Unless a sales tax exemption certificate is received, the current sales tax rate on the date of the invoice will be added.
A69: Structural Steel: | G69: =RECAP!B11 -> 0 | H69: Tons | R69: Sincerely,
A70: Steel Joist: | G70: ='J&D'!B8 -> 0 | H70: Pc's | I70: ='J&D'!C8 -> 0 | J70: Tons | R70: =RECAP!K3 -> 0
A71: Metal Deck: | G71: ='J&D'!B17 -> 0 | H71: Squares | O71: E-Mail: | R71: =RECAP!I4 -> E-Mail
A72: Escalation is Based on Today's Prices. Quote is valid for seven (7) days after which time pricing it is subject to review.
A73: SEE BELOW TERMS AND CONDITIONS WHICH ARE INCORPORATED INTO THIS PROPOSAL AND CONTRACT WITH CUSTOMER (BUYER).
A75: STANDARD TERMS & CONDITIONS OF SALE
A76: ARTICLE 1 – PROPOSAL TERMS AND CONTRACT DOCUMENTS:
A77: 1.1 | B77: These Standard Terms & Conditions of Sale are part of Hancock Structural Steel, LLC’s (“Seller”) Proposal (the “Proposal”). “Buyer” or “Buyer” means the Buyer listed in the Proposal.
A78: 1.2 | B78: PROPOSAL TERMS. This offer is expressly limited to these terms, and any attempt to add to such terms shall be deemed a rejection and a counteroffer, which may result in a withdrawal of this Proposal or a modification in price.
A79: 1.2.1 | C79: If this Proposal is accepted, and the Buyer’s order is issued for that purpose, it is expressly agreed that the terms and conditions of this Proposal shall prevail insofar as the same may in any way conflict with the terms and conditions set forth in the Buyer’s order form, and the issuance of such order form by the Buyer shall be deemed to be the Buyer’s assent to the foregoing.
A80: 1.2.2 | C80: If, as a result of this provision, Seller is asked or required to enter into a separate written agreement beyond the terms of this Proposal, then, in that event, Seller reserves the right to review the general terms and conditions of the proposed agreement and the right to reject any and all terms and conditions of said agreement which are in conflict with or vary the terms of this Proposal.
A81: 1.2.3 | C81: Time Limit of Proposal. Unless modified by the Proposal or given a directive to proceed resulting in a Contract as set forth in Article 1.3, the Proposal shall be valid for seven (7) days from the date provided thereon, and thereafter shall automatically terminate unless extended in writing by Seller. The Proposal is made with reference to steel prices in effect on the date of the Proposal. This Proposal may be changed or revoked at any time by Seller prior to acceptance.
A82: 1.3 | B82: CONTRACT. In the event, prior to the execution of a mutually agreeable contract, that Seller is directed to purchase material, begin the shop drawing process, or otherwise commence any of the work contemplated by this Proposal, this Proposal shall be deemed accepted, and becomes a binding agreement. Seller reserves the right to refuse or negotiate terms of any other proposed agreement presented by the Buyer as a substitution to these STANDARD TERMS & CONDITIONS OF SALE.
A83: 1.3.1 | C83: No terms and conditions contained in the agreement between Owner and Buyer, if applicable, shall be binding on Seller unless a copy of such terms and conditions has been furnished to Seller and accepted in writing signed by the Seller.
A84: 1.3.2 | C84: The parties expressly agree that this Proposal embodies their entire Contract; any subsequent cancellations or modifications must be agreed upon in writing.
A85: 1.3.3 | C85: Buyer and Seller agree that Seller’s Scope of Work is limited to the structural steel shown or noted on the structural design drawings only (“Work”).
A86: 1.3.4 | C86: Contract Documents. Unless agreed to by Seller in writing, the Contract Documents are limited to the plans and specifications specifically referenced in the Proposal and these Standard Terms & Conditions of Sale (“Contract Documents”). If there is any conflict among the provisions of the Proposal, these Standard Terms & Conditions of Sale, the referenced plans and specifications, or Buyer’s acceptance (hereinafter collectively called “Contract”), the documents shall govern in the order just given.
A87: 1.4 | B87: CODE OF STANDARD PRACTICE. Buyer and Seller agree that the Work shall be performed in accordance with the terms of these Standard Terms and Conditions of Sale and the American Institute of Steel Construction Code of Standard Practice for Buildings and Bridges (“CoSP”), in the addition specified in the Contract Documents, and if none is specified, the current edition of the CoSP.
A88: 1.5 | B88: PLANS AND SPECIFICATIONS. Seller shall be entitled to rely upon the plans and specifications provided to it by Buyer. Seller is not responsible for the suitability, adequacy, or building code conformance of the design or information provided by others, including the Contract Documents, nor does it assume responsibility for determining that the Owner’s requirements have been included in the design documents and specifications provided by others.
A89: 1.5.1 | C89: If the design is not complete at the time of the Proposal, released for construction drawings and approved shop drawings will be required before material purchases or fabrication can commence. Seller reserves the right to seek an equitable adjustment to the Contract Time or Contract Sum if the design drawings are incomplete.
A90: 1.6 | B90: SCOPE OF WORK. Materials will be fabricated in accordance with structural design drawings and specifications and with detailed shop drawings as approved by Owner or Owner’s authorized representatives (also known as “Products”). Seller will perform shop inspections in accordance with Owner’s requirements, to the extent they are expressly provided for in the structural steel specifications, as well as applicable AISC, AWS and AASHTO standards. Buyer, at its expense, must set, drill, grout, and tighten anchor bolts for steel members. Unless otherwise provided in the Proposal, Seller’s price does not include costs associated with field measurements, site surveys, shop inspection by independent 3rd party agencies, removal of hauling residue, field cleaning of any stain resulting from steel oxidization, field touch-up paint, painting, galvanizing, or supply of miscellaneous metals, embedded items, scuppers, drains, railings, conduit hangers or supports, shims, expansion dams, neoprene joints, sealing materials, grout, shear studs, or bolts other than connection bolts for supplied items.
A91: 1.7 | B91: PERMITS & LICENSES. Buyer shall obtain, without cost to Seller, all permits, licenses, easements, and environmental approvals necessary for the execution of the Contract.
A92: ARTICLE 2 – TERMS OF PAYMENT:
A93: 2.1 | B93: CONTRACT SUM. The Contract Sum shall be as set forth on the face of the Proposal.
A94: 2.2 | B94: SCHEDULE OF VALUES. Seller will submit a Schedule of Values for progress invoicing.
A95: 2.3 | B95: TIME FOR PAYMENT. Payment shall be made to Seller within thirty (30) days of the date of Seller’s invoice.
A96: 2.4 | B96: REMEDIES FOR NON-PAYMENT. If Buyer does not pay Seller any amount due under this Contract or any other agreement when such amount is due, such shall be deemed in material breach of Contract, and Seller may, without liability to Buyer, and without prejudice to Seller’s other lawful remedies (i) terminate Seller’s obligations under this Contract; (ii) declare immediately due and payable all Buyer’s obligations to Seller; (iii) change credit terms with respect to any further work, including, but not limited to, receipt of cash in advance of further shipment for amounts owed or to be owed; (iv) suspend or discontinue any further work and, if suspended, the time to complete the Contract shall be extended for the period of such suspension; and/or (v) repossess the Products. The Contract amount shall be increased, by appropriate adjustment, by the amount of Seller’s demobilization, delay, and remobilization costs.
A97: 2.5 | B97: NO OFFSET OR SET-OFF. Buyer shall not set-off amounts due to any alleged claims against Seller on this Project or any other project.
A98: 2.6 | B98: SERVICE CHARGES. Payments not received when due shall incur service charges at the rate of one and a half percent (1.5%) per month (18% per annum) until paid.
A99: 2.7 | B99: NO CONTINGENT PAYMENTS. Payments due to Seller are not contingent upon payments by others nor shall Seller waive its lien rights prior to receiving payments due.
A100: 2.8 | B100: NO RETAINAGE. The Buyer agrees to pay the full purchase price stated in this Proposal. Retainage may not be withheld without the specific written consent of Seller. There will be no withholding of monies from Seller’s payments. Deductive change orders or back charges may not be withheld from any payments due Seller without written consent of Seller. Any disputed deductive change orders or back charges shall be resolved as set forth in Article 11.
A101: 2.9 | B101: NO PERFORMANCE OR PAYMENT BOND. The quoted price does NOT include the cost of a performance or payment bond Unless otherwise provided in the Proposal.
A102: 2.1 | B102: ADEQUATE ASSURANCES. In the event a reasonable doubt exists as to the Buyer’s financial responsibility, Seller shall have the right, in addition to all others it may possess, to stop operations, withhold shipment and recall in transit, and/or require a full or partial cash payment, until the Buyer shall have paid for all material previously delivered or satisfied Seller of Buyer’s financial responsibility and ability to pay the full Contract price. Seller shall have no obligation to begin or continue performance until adequate credit and funding information is provided, at any time on request of Seller. Seller may stop the manufacture or supply of any labor or materials when it, in its sole discretion, determines that Buyer is in breach of this Agreement or any other Contract with Seller or Seller has insecurity with respect to funding or creditworthiness, until payment is made, and any dispute or insecurity has been resolved.
A103: 2.11 | B103: LIEN WAIVERS: Nothing in the Contract Documents shall cause to be voided or diminished in any manner Seller’s right to enforce its mechanic’s lien rights or obtain payment under an applicable payment bond if Seller is not timely paid. Seller will only execute unconditional and/or final lien waivers for amounts actually received and any lien waivers shall only relate to the actual Work performed and not future Work or future payments. Any form or release wherein the Subcontractor purports to release the Contractor, Owner, or Design Professional is hereby qualified by the following language, whether or not the Subcontractor specifically adds the language: “This release shall apply only to work for which payment has been received in full by Seller, and it shall not apply to retainage, unbilled changes, or amounts not yet paid.”
A104: ARTICLE 3 – LIMITATIONS ON WARRANTIES AND LIABILITIES:
A105: 3.1 | B105: DUTY TO INSPECT PRIOR TO ERECTION. All claims against Seller will be deemed waived unless made in writing within the earlier of, five (5) calendar days of delivery or two (2) days prior to erection. Claims against Seller will be waived unless Seller is given adequate opportunity to inspect, approve, and, if required, correct the cause of the claim. The provision includes, but is not limited to, errors, material defects, faulty workmanship, shortages, and assessments. A representative of Seller must authorize all claims. No claim will be allowed for corrections of alleged errors in materials fabricated by Seller unless Seller is notified before the corrections are made and Seller’s responsibility is proven.
A106: 3.2 | B106: LIMITED WARRANTY: Seller warrants that the work described in the Contract shall be free from defects in workmanship and material, which vary from the Contract Documents. Seller shall replace or repair any such faulty workmanship or defective material, which varies from the Contract Documents, provided that it is reported in writing to Seller (a) five (5) calendar days after delivery for defects which can be discovered upon a reasonable inspection, or (b) for latent defects, one (1) year from date of on which seller last delivers materials or services within the Scope of this Contract (“Warranty Period”). THE LIABILITY OF SELLER IS LIMITED TO THE REPAIR AND REPLACEMENT OF ANY DEFECTIVE MATERIALS OR PARTS THEREOF AT ITS SHOP, OR AT SUCH OTHER LOCATION AS SELLER, IN ITS SOLE OPTION SHALL DESIGNATE.
A107: 3.2.1 | C107: Seller shall be allowed time to inspect and verify a claim and shall have access to all performance data. No credit will be allowed for any cost or expense Buyer may incur in replacing or correcting materials or workmanship hereunder or for charges for labor or materials furnished by Buyer unless Buyer has obtained Seller’s prior written approval.
A108: 3.3 | B108: NO OTHER WARRANTIES. THE WARRANTIES SET FORTH IN THIS ARTICLE ARE EXCLUSIVE & IN LIEU OF ALL OTHER WARRANTIES WHETHER STATUTORY, EXPRESS, OR IMPLIED (INCLUDING ALL WARRANTIES OF MERCHANTABILITY & FITNESS FOR PARTICULAR PURPOSE AND/OR WARRANTIES ARISING FROM COURSE OF DEALING OR USAGE OF TRADE). THE REMEDIES PROVIDED ABOVE ARE THE BUYER’S SOLE REMEDIES FOR ANY FAILURE OF SELLER TO COMPLY WITH ITS OBLIGATIONS. SELLER HEREBY DISCLAIMS AND EXCLUDES ALL OTHER WARRANTIES. Any other statement in Contract Documents shall not be deemed to constitute a warranty.
A109: 3.4 | B109: LIMITATION OF REMEDIES. Corrections of non-conformities in the manner and for the period of time provided above shall constitute fulfillment of all liabilities of Seller to Buyer, whether based on warranty, contract, strict liability, negligence, willfulness or any other legal theory. IN NO EVENT SHALL SELLER BE LIABLE TO BUYER OR OTHER THIRD PARTIES FOR ANY SPECIAL, INDIRECT, INCIDENTAL OR CONSEQUENTIAL DAMAGES OR LOST PROFIT ARISING OUT OF OR IN ANY WAY CONNCETED WITH SELLER’S WORK UNDER THIS AGREEMENT.
A110: 3.5 | B110: ACCEPTANCE AND ACKNOWLEDGMENT. Acceptance of the Products shall occur if no written notice is made in writing, as set forth in Article 3.1, within the earlier of, five (5) calendar days of delivery or two (2) days prior to erection. By acceptance of the fabricated Products described on this Proposal, Buyer acknowledges that the limitations, disclaimers and terms set forth herein are conditions of the sale and that they constitute the entire agreement between Seller and Buyer regarding warranty or any other liability or damages.
A111: 3.6 | B111: DEFECTS BY OTHERS. Seller shall NOT be liable for any damages attributable to the Buyer or workmanship by others. THERE IS NO WARRANTY and Seller shall not be obligated to replace or repair all or any part of the work when such defects are not directly attributable to defects in Seller’ workmanship or material, such as, but not limited to, defects caused by operating abuse, neglect, erosion, corrosion, force majeure or other similar causes beyond Seller’ control.
A112: 3.7 | B112: PRODUCTS NOT FABRICATED BY SELLER. Seller’s sole obligation with respect to products not manufactured or produced by Seller or services directly rendered by Seller shall be limited to assigning or transferring to Buyer any written warranty extended to Seller by the manufacturer of such products or subcontractor of such services to the extent such warranty may be so assigned.
A113: 3.8 | B113: EFFECTIVE DATE OF WARRANTIES. The only warranties made by Seller are those expressly stated in this Article 3, and while it begins to run on the date of delivery, it shall not be effective until full and final payment of the Contract amount, including all adjustments thereto, has been received by Seller.
A114: 3.9 | B114: LIMITATION OF LIABILITY. The remedies of Buyer set forth in Article 3 are exclusive, and the total liability of Seller with respect to the Contract or anything done in connection therewith, such as the timeliness or quality of performance or lack thereof, whether in Contract, in tort (including negligence and strict liability), in warranty or otherwise shall not exceed ten percent (10%) of the amount paid to Seller on account of this Contract. Seller shall not be responsible for any liquidated damages or penalties related to time of performance or delays. Seller shall not be liable for work being done without its prior knowledge or consent.
A115: ARTICLE 4 – INDEMNIFICATION:
A116: 4.1 | B116: Buyer hereby releases and agrees to indemnify, defend and hold harmless Seller, its shareholders, officers, agents, employees, affiliates, successors, assigns and third-party suppliers (“Seller’s Indemnified Parties”) from and against any and all direct and indirect claims, debts, actions, causes of action, liabilities, loss, suits, demands, fines, penalties, judgments, omissions, damages or expenses whatsoever, including, without limitation, attorneys’ fees and costs (“Damages”) incurred by or against Seller or any of Seller’s Indemnified Parties due to or arising out of, in connection with, resulting from or relating to (i) misrepresentations, breach of the warranties, representations, covenants or agreement contained in this Contract or any law by Buyer or any of Buyer’s shareholders, directors, officers, employees, affiliates, representatives, agents, successors or assigns (“Buyer’s Parties”), or (ii) any damage to or destruction of property, or injury to or death of persons caused, or alleged to have been caused, in whole or in part, by any intentional, reckless, negligent or other act (or failure to act) of Buyer or any of Buyer’s Parties, or (iii) losses, damages or injuries caused by Buyer’s products, Buyer’s specifications, designs, approvals or instructions provided to Seller, or due to improper application or use of the Products or otherwise. Prior to settling any claim, Buyer will give Seller an opportunity to participate in the defense and/or settlement of such claim. Buyer shall not settle any claim without Seller’s written consent. In the event of any recall affecting the Products, Seller shall have the right to control the recall process and Buyer shall fully cooperate with Seller in connection with the recall.
A117: ARTICLE 5 – TITLE & RISK OF LOSS:
A118: 5.1 | B118: TITLE TO WORK. The title and right of possession of the Work shall remain in Seller whatever may be the mode of its attachment to realty or other property, until all payments are made in accordance with this Contract. Title shall pass to Buyer upon payment being fully made as set forth in this Contract.
A119: 5.2 | B119: RIGHT OF POSSESSION. Where Buyer has failed to make a payment within the allowed time, Seller may declare all remaining payments due and payable and, in exercise of its right of possession, shall have right of entry to the premises where the work is located and the right to remove the work from the premises. If the sum of the resale of salvage value of the work so removed and all payments made by Buyer exceeds the total damages (including consequential damages) to Seller, Seller will pay the excess amount to Buyer.
A120: 5.3 | B120: SECURITY INTEREST. Notwithstanding the foregoing, and as a precaution in case a court or an arbitrator deems title to the work to pass to Buyer prior to the full payment of the Contract price, Buyer hereby grants to Seller, in partial consideration for Seller’s sale of the Products and/or work, and Seller hereby retains a security interest in all Products sold to Buyer and documents relating to such Products or work now or hereafter in the possession of or under the control of Buyer, title to which might at any time be determined to have passed to Buyer including, without limitation, insurance proceeds and proceeds from the Buyer’s Contract with the owner listed therein, to secure Buyer’s obligations to Seller under this contract and all other obligations of Buyer to Seller. Buyer (i) authorizes Seller to execute, on Buyer’s behalf such financing statements, continuation statements and (ii) agrees to execute such other documents including, but not limited to pledge agreements, and to take such actions as may be required by Seller to evidence or perfect the security interest granted herein and the interest of Seller.
A121: 5.4 | B121: RISK OF LOSS. Buyer assumes all risk of loss after accepting care, custody, and control of any or all parts of the work. Owner or Buyer shall carry and maintain All Risk or Builder’s Risk insurance throughout the duration of the Project to cover all materials provided by Seller, and Seller shall be an additional named insured under such insurance policy.
A122: ARTICLE 6 – CONTRACT TIME:
A123: 6.1 | B123: CONTRACT TIME. Seller shall only be bound to the project schedule to the extent it is specifically incorporated as a Contract Document on the face of this Proposal; otherwise, Seller shall perform the Work within a reasonable amount of time (“Contract Time”). If a schedule is expressly listed on the face of this Proposal, any modification to the agreed upon schedule shall allow Seller a reasonable time to complete its Work in an efficient manner considering the contract completion date and any interim times set forth in the project schedule. Seller’s ability to meet the required schedule is based on Buyer’s provision of contract drawings that comply with Section 3.1 of the AISC Code of Standard Practice at the time of bidding. Drawings must be clear and provide all details required for the preparation of shop drawings and fabrication. In the event RFIs are issued by Seller, schedule impacts should be expected.
A124: 6.1.1 | C124: In the absence of an agreed delivery schedule, Seller will produce, deliver and invoice as its production schedule permits, and Buyer’s failure to accept delivery or pay for stored materials on or before the Storage, Material & Delivery Escalation Date will make it subject to the Escalation Rate of two and a half (2.5%) per month for each month of delay on the unpaid portion of the Sale Price.
A125: 6.2 | B125: FORCE MAJEURE. If the performance of the Contract by Seller is interrupted by any cause beyond the reasonable control of Seller, whether similar or dissimilar, foreseen or unforeseen, foreseeable or unforeseeable, existing or future, Seller shall be excused from the performance of this Contract while and to the extent it is prevented from so performing by any one or more of such causes: (1) labor shortages, strikes, labor disputes, whether or not the demands of Seller shall be reasonable and within the power of either party to concede, or other inability to obtain necessary labor; (2) acts of God, including, but not limited to, epidemic, quarantine, flood, earthquake, wind, hurricane or other inclement weather; (3) changes in laws, proclamations, acts, regulations, ordinances, demands or requirements of any governmental authority; (4) explosions, accidents, sabotage, revolution or insurrection, acts of terrorism, civil commotion, blockade, embargo; (5) lack of or failure of or other inability to obtain necessary transportation, fuel, power, materials, machinery, raw materials, supplies, equipment or facilities, delays caused by other contractors, subcontractors or their subcontractors of any tier, or any materialmen or suppliers (including the suppliers of metal deck) Any such delay shall extend the time for completion of the Contract by not less than the duration of the delay. Additional costs incurred to complete, repair and/or replace any portion of the work due to a force majeure event shall be compensable to Seller, whether or not a change order for this work has been issued.
A126: 6.3 | B126: STORAGE COSTS AND MATERIALS. If the Buyer declines to accept delivery beyond the mutually agreed delivery date, a charge of $10.00 per square foot of space for storing raw and fabricated materials will be assessed to cover Seller’s storage, protection and finance costs; however, should Seller have to store materials offsite due to lack of available space, Buyer shall pay the actual storage costs incurred by Seller. Buyer shall also be responsible for paying for all temporary protection measures for such stored materials. Additionally, if the mutually agreed delivery date exceeds the Storage, Material & Delivery Escalation Date, the price shall be increased two and a half (2.5%) for each month of delay on the unpaid portion of the Sale Price beyond the Storage, Material & Delivery Escalation Date.
A127: 6.3.1 | C127: Handling costs incurred by Seller to move materials to and/or from the storage area or to handle material of other projects to accommodate storage of this project shall be charged at $100.00 per hour. Moving/handling equipment time will be charged at $485.00 per hour.
A128: 6.3.2 | C128: Buyer shall assume all risks for damage and weathering to any material stored at Buyer’s request.
A129: 6.4 | B129: EQUITABLE ADJUSTMENT. This Proposal is based upon: Seller’s timely receipt of Buyer’s notice to proceed; Issued for Construction Drawings, which comply with Section 3.1 of the AISC Code of Standard Practice, current edition; return of approved shop drawings as set forth in this Agreement; and prompt return of RFI responses to Seller. Seller shall be entitled to an equitable adjustment in the Contract Time and Contract Sum, including but not limited to, any increased costs of labor (including, but not limited to, rescheduling work, paint touch-up or repainting, additional handling, increases in labor or subcontract rates, etc.), overtime, and materials resulting from any change of drawings, change of schedule, acceleration, out of sequence work or delay caused by others for whom Seller is not responsible.
A130: 6.5 | B130: DELAYS OR SUSPENSIONS OVER 30 DAYS. To the extent the Project is suspended or delayed for a total of thirty (30) days, which days do not need to be consecutive, for causes beyond Seller’s control, Seller shall have the option to deem the Buyer in material breach, terminate the Contract, and stop work on the Project. If Seller elects to stop work due to this material breach, Seller shall be entitled to be paid for the value of work completed to date, including, but not limited to, stored materials, detailing, material and labor escalation, work in progress and any “wind down” expenses. In addition, Seller shall be entitled to its anticipated profit and overhead expense on the entire Contract, its unabsorbed shop overhead and expenses and its appurtenant costs and expenses, including, but not limited to, consulting and actual attorney’s fees.
A131: ARTICLE 7 – CHANGES:
A132: 7.1 | B132: LIMITATION ON UNIT PRICES. Buyer recognizes that the prices in this Agreement are based upon Seller’s determination of the material and labor required to construct the structural steel elements based upon the Contract Documents listed in the Proposal. Changes made after the date of the Proposal shall be priced based on elements of the work and shall not be subject to unit prices.
A133: 7.2 | B133: DESIGN DRAWING CHANGES. Upon Seller’s receipt of the Released for Construction (“RFC”) drawings or subsequent changes to the RFC drawings, Seller shall review for variations and changes (“Design Drawing Changes”) from the bid documents included with this Contract. Seller shall be entitled to an equitable adjustment in the Contract Sum or Contract Time or both, in the event of increased quantities, complexity, labor, materials, or scope shown on the RFC drawings differ from the bid documents.
A134: 7.3 | B134: CONDITIONS PRECEDENT TO CHANGE ORDER WORK. Seller shall suspend performance of any change, whether directed by Buyer or suggested by Seller, unless the following conditions precedent are satisfied: (1) Seller is thereafter released in writing by Buyer to perform said change, (2) Buyer and Seller shall mutually agree in writing upon an equitable adjustment in the price and/or delivery date to reflect the effect of such change, (3) Buyer has timely paid all amounts owed under the original scope of Work in accordance with the Contract, (4) Buyer has reviewed and paid for all Buyer caused Changes within thirty (30) days of issuance of the change order request, (5) Buyer shall continue to make payments in accordance with the Contract Documents and (6) for Owner-caused Changes.
A135: 7.4 | B135: DIFFERING CONDITIONS. If conditions are encountered at the site which are concealed physical conditions which differ from those indicated in any plans, specifications, reports, surveys, or other information provided to Seller, then the Contract Sum shall be equitably adjusted for such concealed or unknown conditions by Change Order upon the claim of either party.
A136: 7.5 | B136: ESCALATION. Seller’s Contract Sum (including but not limited to labor, material, transportation prices) are based on current prices at the time of the Proposal. Any significant price increases (meaning a price increase exceeding 1.5% of the price at time of the Proposal) in materials, transportation, labor, or other services necessary to perform the Work that occur during the period of time between the date of the Proposal and substantial completion of the Project, shall cause the Contract Sum to be equitably adjusted by an amount reasonably necessary to cover any such increase. Likewise, if the completion of the Work is extended more than six (6) months beyond the anticipated substantial completion for such Work, then the Contract Sum shall also be equitably adjusted to account for inflation and rate increases.
A137: ARTICLE 8 – DELIVERY & FREIGHT:
A138: 8.1 | B138: PAINT WARNING. Structural steel will be delivered with one (1) coat standard HSS shop primer. Your special attention is called to the use of extreme care and appropriate handling equipment required during unloading, rotation girders to web vertical position, erection, and subsequent field operations. Seller will not be responsible for any field touch-up required due to failure to properly protect the paint system after delivery F.O.B. jobsite.
A139: 8.2 | B139: DELIVERY. Delivery by truck will be F.O.B. destination with freight allowed to the nearest accessible point to the jobsite. Access is deemed to be an improved road that allows the truck to operate under its’ own power without jeopardizing the safe operation of the vehicle and the safety of the driver. The driver has full rights to assess the access and the right to deny delivery to the unloading point if he/she feels that he is jeopardizing his/her safety and/or the safe operation of the truck.
A140: 8.3 | B140: FREIGHT ALLOWANCE. The freight allowance does not include charges for unloading, switching, spotting, excess time, cartage, demurrage or other similar services, all of which will be additional charges to Buyer if performed by Seller, costs will be billed to Buyer at 120% of the costs billed to Seller.
A141: 8.3.1 | C141: The freight allowance for truck deliveries is based on full truckloads, should the Buyer request shipments requiring smaller loads than planned a corresponding change order will need to be issued and executed.
A142: 8.3.2 | C142: The freight allowance includes two (2) hours at the jobsite for unloading each truck delivery. Buyer agrees to promptly provide labor, cranes, or other equipment necessary to timely unload materials.
A143: 8.3.3 | C143: If Seller ships anchor bolts, bearings, embedded items, etc. in advance, Buyer will be responsible for unloading and providing a safe and secure storage of same.
A144: 8.3.4 | C144: Unless otherwise provided in the Proposal, truck deliveries will be weekdays, during Seller’s normal working hours. Shipments requiring after working hours delivery will be charged an additional amount of $500.00 per load.
...

Sheet COST CODES
G1: Quote # | H1: =RECAP!K1 -> E26-XXX
G2: Date: | H2: =TODAY() -> 46238
G3: Estimator: | H3: =RECAP!K3 -> 0
G4: Job #:
A5: =RECAP!C10 -> 0
A6: =RECAP!I10 -> (City, State)
A7: Cost Code: | C7: Description: | G7: Cost: | H7: Vendor:
A8: 01-970 | C8: Procore Pay/Textura Fee Including Sales Tax | G8: =RECAP!D52 -> 0
A9: 05-010 | C9: Detailing | G9: =RECAP!D25 -> 0 | H9: =RECAP!J25 -> 0
A10: 05-011 | C10: Engineering | G10: =RECAP!D26 -> 0 | H10: =RECAP!J26 -> 0
A11: 05-012 | C11: BIM | G11: =RECAP!D27 -> 0 | H11: =RECAP!J27 -> 0
A12: 05-105 | C12: Structural Material | G12: =RECAP!D28 -> 0
A13: 05-106 | C13: Bolts/Fasteners | G13: =RECAP!D29 -> 0
A14: 05-110 | C14: =RECAP!D15 -> 0 | D14: Hrs | E14: Outsourced Fabrication | G14: =RECAP!D30 -> 0 | H14: =RECAP!J30 -> 0
A15: 05-121 | C15: =Labor!B13-SUM(Labor!B4:B6) -> 0 | D15: Hrs | E15: Structural Fabrication | G15: =RECAP!D31 -> 0
A16: 05-122 | C16: Galvanizing | G16: =RECAP!D32 -> 0
A17: 05-123 | C17: =Labor!B4+Labor!B18 -> 0 | D17: Hrs | E17: Processing Steel | G17: =Labor!D4+Labor!D18 -> 0
A18: 05-124 | C18: Steel Rolling | G18: =RECAP!D33 -> 0
A19: 05-210 | C19: Joist and Deck | G19: =RECAP!D34 -> 0 | H19: =RECAP!J34 -> 0
A20: 05-301 | C20: Anchor Bolts | G20: =RECAP!D35 -> 0
A21: 05-302 | C21: =Labor!B5+Labor!B19 -> 0 | D21: Hrs | E21: Shop Priming (Labor & Material) | G21: =RECAP!D36 -> 0
A22: 05-303 | C22: Grating | G22: =RECAP!D37 -> 0
A23: 05-305 | C23: Outsourced Paint | G23: =RECAP!D38 -> 0 | H23: =RECAP!J38 -> 0
A24: 05-306 | C24: Outsourced Shot Blasting | G24: =RECAP!D39 -> 0 | H24: =RECAP!J39 -> 0
A25: 05-400 | C25: =Labor!B6+Labor!B20 -> 0 | D25: Hrs | E25: Load/Unload Material | G25: =Labor!D6+Labor!D20 -> 0
A26: 05-401 | C26: Jobsite Freight (Material Delivery) | G26: =RECAP!D40 -> 0
A27: 05-500 | C27: =Labor!B27-SUM(Labor!B18:B20) -> 0 | D27: Hrs | E27: Misc. Fabrication | G27: =RECAP!D41-Labor!D18-Labor!D19-Labor!D20 -> 0
A28: 05-510 | C28: Misc. Material | G28: =RECAP!D42 -> 0
A29: 05-600 | C29: Steel Erection | G29: =RECAP!D43 -> 0 | H29: =RECAP!J43 -> 0
A30: 05-601 | C30: Misc. Material & Erection | G30: =RECAP!D44 -> 0 | H30: =RECAP!J44 -> 0
A31: 05-602 | C31: Subcontractor Other | G31: =RECAP!D45 -> 0 | H31: =RECAP!J45 -> 0
A32: 05-999 | C32: Allowance(s) | G32: =RECAP!D46 -> 0
C33: HSS Contingency | G33: =RECAP!D47 -> 0
A34: 17-994 | C34: Insurance | G34: =RECAP!D48 -> 0
A35: 17-996 | C35: Performance/Payment Bond | G35: =RECAP!D51 -> 0
A36: Subtotal: | G36: =SUM(G8:G35) -> 0
A37: Total Profit for Project: | G37: =RECAP!G53-'COST CODES'!G36 -> 0
A38: Grand Total: | G38: =SUM(G36:G37) -> 0
E40: Difference from Proposal Amount: | G40: =RECAP!G53-'COST CODES'!G38 -> 0

Sheet Estimator Notes
A1: Project Name: | B1: Estimate Number: | C1: Bid Date: | D1: Drawing Date: | E1: Notes:
A2: =RECAP!C10 -> 0 | B2: =RECAP!K1 -> E26-XXX
A8: Addendum #: | B8: Addendum Date: | C8: Addendum Notes:
A16: Date: | B16: Notes:

Sheet Contract Review Record
B2: Contract Review Record
B3: Job Name: | C3: =RECAP!C10 -> 0 | L3: Job #: | M3: 26-
B4: Estimator: | C4: =RECAP!K3 -> 0 | J4: Shop Hrs. | K4: =RECAP!D11 -> 0 | L4: Estimate # | M4: E26-
B5: ITEMS & COMMENTS | N5: Check Box
N6: YES | O6: NO
B7: Specifications & plans received & recorded
B8: All Addendums received and recorded
B9: All plans, specifications, addendums (including post-bid) sent to erector, detailer, engineer, joist & deck suppliers, and any other vendors receiving a subcontract or purchase order? | AQ9: Erected
B10: All vendor quotes saved in estimate folder | AQ10: FOB
B11: Estimator Notes Attached
B12: Scope of Work Attached
B13: List of all sub quotes: | G13: Company: | L13: Type:
B17: Special/ Unusual Materials required list below:
B20: Engineering Required
B21: =[2]RECAP!F30 -> -
B22: Detailing | I22: Company Name
B24: Joist & Deck required
B25: =[2]RECAP!F31 -> -
B26: Special Shipping Instructions
B28: TC Bolt Required?
B30: Fire Proofing
B31: =[2]MATERIALS!B5 -> (any Fire proofing type Y or N)
B32: Surface Preparation / Primer / Finish Paint Instruction of surface rep
B34: Galvanizing | I34: Tons
B36: Are there beams with Camber
B38: Erected or FOB | H38: Who's the Erector?
B40: Lintels
B42: Embeds
B44: Sequencing
B46: Turnover Meeting Required Attendees:
B47: Joshua Waller
B48: Paul Hostetter
B49: Bill Holtfreter
B50: Andy Boyce
B51: Rick Lonsway
B52: Nikki Perkins
B53: Justin Chagnon
